cheshirecat_python_sdk/__init__.py
cheshirecat_python_sdk/client.py
cheshirecat_python_sdk/configuration.py
cheshirecat_python_sdk/enums.py
cheshirecat_python_sdk/utils.py
cheshirecat_python_sdk/builders/__init__.py
cheshirecat_python_sdk/builders/base.py
cheshirecat_python_sdk/builders/memory.py
cheshirecat_python_sdk/builders/settings_input.py
cheshirecat_python_sdk/builders/why.py
cheshirecat_python_sdk/clients/__init__.py
cheshirecat_python_sdk/clients/http_client.py
cheshirecat_python_sdk/clients/websocket_client.py
cheshirecat_python_sdk/endpoints/__init__.py
cheshirecat_python_sdk/endpoints/admins.py
cheshirecat_python_sdk/endpoints/agentic_workflow.py
cheshirecat_python_sdk/endpoints/auth.py
cheshirecat_python_sdk/endpoints/auth_handler.py
cheshirecat_python_sdk/endpoints/base.py
cheshirecat_python_sdk/endpoints/chunker.py
cheshirecat_python_sdk/endpoints/conversation.py
cheshirecat_python_sdk/endpoints/custom_endpoint.py
cheshirecat_python_sdk/endpoints/embedder.py
cheshirecat_python_sdk/endpoints/file_manager.py
cheshirecat_python_sdk/endpoints/health_check.py
cheshirecat_python_sdk/endpoints/large_language_model.py
cheshirecat_python_sdk/endpoints/memory.py
cheshirecat_python_sdk/endpoints/message.py
cheshirecat_python_sdk/endpoints/plugins.py
cheshirecat_python_sdk/endpoints/rabbit_hole.py
cheshirecat_python_sdk/endpoints/users.py
cheshirecat_python_sdk/endpoints/utils.py
cheshirecat_python_sdk/endpoints/vector_database.py
cheshirecat_python_sdk/models/dtos.py
cheshirecat_python_sdk/models/api/admins.py
cheshirecat_python_sdk/models/api/conversations.py
cheshirecat_python_sdk/models/api/factories.py
cheshirecat_python_sdk/models/api/file_managers.py
cheshirecat_python_sdk/models/api/memories.py
cheshirecat_python_sdk/models/api/messages.py
cheshirecat_python_sdk/models/api/plugins.py
cheshirecat_python_sdk/models/api/rabbit_holes.py
cheshirecat_python_sdk/models/api/tokens.py
cheshirecat_python_sdk/models/api/users.py
cheshirecat_python_sdk-1.8.0.dist-info/METADATA
cheshirecat_python_sdk-1.8.0.dist-info/WHEEL
cheshirecat_python_sdk-1.8.0.dist-info/licenses/LICENSE
cheshirecat_python_sdk-1.8.0.dist-info/RECORD
