Metadata-Version: 2.4
Name: cheshirecat-python-sdk
Version: 1.8.0
Summary: Python SDK for the Cloud-ready fork of the Cheshire Cat
Project-URL: Repository, https://github.com/matteocacciola/cheshirecat-python-sdk
Project-URL: Documentation, https://github.com/matteocacciola/cheshirecat-python-sdk#README
Project-URL: Bug Tracker, https://github.com/matteocacciola/cheshirecat-python-sdk/issues
Author: Matteo Cacciola
Maintainer: Matteo Cacciola
License:                     GNU GENERAL PUBLIC LICENSE
License-File: LICENSE
Keywords: Cheshire-Cat,LLM,OpenAPI,OpenSource,RAG
Classifier: Development Status :: 5 - Production/Stable
Classifier: Framework :: FastAPI
Classifier: Programming Language :: Python :: 3
Classifier: Programming Language :: Python :: 3.10
Classifier: Programming Language :: Python :: 3.11
Classifier: Programming Language :: Python :: 3.12
Classifier: Topic :: Scientific/Engineering :: Artificial Intelligence
Requires-Python: >=3.10
Requires-Dist: pydantic
Requires-Dist: pylint
Requires-Dist: pylint-actions
Requires-Dist: python-magic
Requires-Dist: requests-toolbelt
Requires-Dist: websockets
